CHANGELOG.md
polliwog/__init__.py
polliwog/_common/__init__.py
polliwog/_common/shape.py
polliwog/box/__init__.py
polliwog/box/_box_object.py
polliwog/line/__init__.py
polliwog/line/_line_functions.py
polliwog/line/_line_intersect.py
polliwog/line/_line_object.py
polliwog/plane/__init__.py
polliwog/plane/_plane_functions.py
polliwog/plane/_plane_intersect.py
polliwog/plane/_plane_object.py
polliwog/plane/_slicing.py
polliwog/plane/_trimesh_intersections.py
polliwog/pointcloud/__init__.py
polliwog/pointcloud/_pointcloud_functions.py
polliwog/polyline/__init__.py
polliwog/polyline/_array.py
polliwog/polyline/_inflection_points.py
polliwog/polyline/_polyline_object.py
polliwog/polyline/_slice_by_plane.py
polliwog/segment/__init__.py
polliwog/segment/_segment_functions.py
polliwog/shapes/__init__.py
polliwog/shapes/_shapes.py
polliwog/transform/__init__.py
polliwog/transform/_affine_transform.py
polliwog/transform/_apply.py
polliwog/transform/_composite_transform.py
polliwog/transform/_coordinate_manager.py
polliwog/transform/_rodrigues.py
polliwog/transform/_rotation.py
polliwog/transform/_testing_helper.py
polliwog/transform/_viewing.py
polliwog/transform/teapot.npy
polliwog/tri/__init__.py
polliwog/tri/functions.py
polliwog/tri/quad_faces.py
polliwog-2.4.0.dist-info/LICENSE
polliwog-2.4.0.dist-info/WHEEL
polliwog-2.4.0.dist-info/METADATA
polliwog-2.4.0.dist-info/RECORD
