Metadata-Version: 2.1
Name: polliwog
Version: 2.4.0
Summary: 2D and 3D computational geometry library
Home-page: https://polliwog.dev/
License: BSD-2-Clause
Author: Paul Melnikow
Author-email: github@paulmelnikow.com
Requires-Python: >=3.7,<4
Classifier: Development Status :: 4 - Beta
Classifier: Intended Audience :: Developers
Classifier: Intended Audience :: Manufacturing
Classifier: Intended Audience :: Science/Research
Classifier: License :: OSI Approved :: BSD License
Classifier: Operating System :: OS Independent
Classifier: Programming Language :: Python :: 3
Classifier: Programming Language :: Python :: 3.7
Classifier: Programming Language :: Python :: 3.8
Classifier: Programming Language :: Python :: 3.9
Classifier: Topic :: Artistic Software
Classifier: Topic :: Multimedia :: Graphics :: 3D Modeling
Classifier: Topic :: Scientific/Engineering :: Mathematics
Classifier: Topic :: Scientific/Engineering :: Visualization
Requires-Dist: numpy (<1.19.0)
Requires-Dist: ounce (>=1.1.0,<2.0)
Requires-Dist: vg (>=2.0.0)
Project-URL: Documentation, https://polliwog.dev/
Project-URL: Repository, https://github.com/lace/polliwog
